QIDLearningLib_sanchosimoes/metrics_sanchosimoes/__init__.py
QIDLearningLib_sanchosimoes/metrics_sanchosimoes/causality.py
QIDLearningLib_sanchosimoes/metrics_sanchosimoes/data_privacy.py
QIDLearningLib_sanchosimoes/metrics_sanchosimoes/data_utility.py
QIDLearningLib_sanchosimoes/metrics_sanchosimoes/performance.py
QIDLearningLib_sanchosimoes/metrics_sanchosimoes/qid_specific.py
QIDLearningLib_sanchosimoes/structure_sanchosimoes/__init__.py
QIDLearningLib_sanchosimoes/structure_sanchosimoes/grouped_metric.py
QIDLearningLib_sanchosimoes/test_sanchosimoes/__init__.py
QIDLearningLib_sanchosimoes/test_sanchosimoes/causality.py
QIDLearningLib_sanchosimoes/test_sanchosimoes/data_privacy.py
QIDLearningLib_sanchosimoes/test_sanchosimoes/data_utility.py
QIDLearningLib_sanchosimoes/test_sanchosimoes/performance.py
QIDLearningLib_sanchosimoes/test_sanchosimoes/qid_specific.py
QIDLearningLib_sanchosimoes/util_sanchosimoes/__init__.py
QIDLearningLib_sanchosimoes/util_sanchosimoes/data.py
QIDLearningLib_sanchosimoes/util_sanchosimoes/stats.py
qidlearninglib_sanchosimoes-0.0.1.dist-info/METADATA
qidlearninglib_sanchosimoes-0.0.1.dist-info/WHEEL
qidlearninglib_sanchosimoes-0.0.1.dist-info/licenses/LICENSE
qidlearninglib_sanchosimoes-0.0.1.dist-info/RECORD
