Metadata-Version: 2.3
Name: QIDLearningLib_sanchosimoes
Version: 0.0.1
Summary: A Python library that provides various metrics that may be used in the quasi-identification recognition process. These metrics measure data privacy, data utility, performance of the QID recognition and others.
Project-URL: Homepage, https://github.com/smartlord7/QIDLearningLib
Project-URL: Issues, https://github.com/smartlord7/QIDLearningLib/issues
Author-email: Sancho Amaral Simões <sanchoamaralsimoes@gmail.com>
License-File: LICENSE
Classifier: License :: OSI Approved :: GNU General Public License v3 (GPLv3)
Classifier: Operating System :: OS Independent
Classifier: Programming Language :: Python :: 3
Requires-Python: >=3.8
